PCAViz/LICENSE.md
PCAViz/PCAViz.py
PCAViz/README.md
PCAViz/__init__.py
PCAViz/examples/1J8K_example.dcd
PCAViz/examples/1J8K_example.pdb
PCAViz/examples/1J8K_example.psf
pcaviz_durrantlab-1.2.data/scripts/pcaviz
pcaviz_durrantlab-1.2.dist-info/METADATA
pcaviz_durrantlab-1.2.dist-info/WHEEL
pcaviz_durrantlab-1.2.dist-info/top_level.txt
pcaviz_durrantlab-1.2.dist-info/RECORD
