Metadata-Version: 2.1
Name: pcaviz-durrantlab
Version: 1.2
Summary: A script to compress molecular dynamics simulations so they can be visualized with PCAViz in a web browser.
Home-page: http://git.durrantlab.com/jdurrant/pcaviz
Author: Jacob Durrant
Author-email: durrantj@pitt.edu
License: UNKNOWN
Platform: UNKNOWN
Classifier: License :: OSI Approved :: GNU General Public License v2 (GPLv2)
Classifier: Operating System :: OS Independent
Requires: scikit_learn (>=0.19.1)
Requires: numpy (>=1.15.2)
Requires: MDAnalysis (>=0.17.0)
Requires-Dist: scikit-learn (>=0.19.1)
Requires-Dist: numpy (>=1.15.2)
Requires-Dist: MDAnalysis (>=0.17.0)
